{
  "mainAssemblyName": "BlazorWASMDemoApp",
  "resources": {
    "hash": "sha256-s4XCZPiw9sreYO7HBXZ65X8wjQwj5Ho0i6ihKZmRZZA=",
    "fingerprinting": {
      "Microsoft.AspNetCore.Components.52uh4rvy1k.wasm": "Microsoft.AspNetCore.Components.wasm",
      "Microsoft.AspNetCore.Components.Forms.sxuye9wrru.wasm": "Microsoft.AspNetCore.Components.Forms.wasm",
      "Microsoft.AspNetCore.Components.Web.uo04nwswhb.wasm": "Microsoft.AspNetCore.Components.Web.wasm",
      "Microsoft.AspNetCore.Components.WebAssembly.ed2mpgo6c2.wasm": "Microsoft.AspNetCore.Components.WebAssembly.wasm",
      "Microsoft.Extensions.Configuration.pvawjtuhi4.wasm": "Microsoft.Extensions.Configuration.wasm",
      "Microsoft.Extensions.Configuration.Abstractions.qycoarjeru.wasm": "Microsoft.Extensions.Configuration.Abstractions.wasm",
      "Microsoft.Extensions.Configuration.Json.j66pezmcjo.wasm": "Microsoft.Extensions.Configuration.Json.wasm",
      "Microsoft.Extensions.DependencyInjection.vdgbrs4or0.wasm": "Microsoft.Extensions.DependencyInjection.wasm",
      "Microsoft.Extensions.DependencyInjection.Abstractions.l9716jag6r.wasm": "Microsoft.Extensions.DependencyInjection.Abstractions.wasm",
      "Microsoft.Extensions.Logging.dypcmt2k1c.wasm": "Microsoft.Extensions.Logging.wasm",
      "Microsoft.Extensions.Logging.Abstractions.41c3tqmqvg.wasm": "Microsoft.Extensions.Logging.Abstractions.wasm",
      "Microsoft.Extensions.Options.ffu15vsa0k.wasm": "Microsoft.Extensions.Options.wasm",
      "Microsoft.Extensions.Primitives.wdgxpgsqcr.wasm": "Microsoft.Extensions.Primitives.wasm",
      "Microsoft.JSInterop.osc8jgovue.wasm": "Microsoft.JSInterop.wasm",
      "Microsoft.JSInterop.WebAssembly.lsljofql11.wasm": "Microsoft.JSInterop.WebAssembly.wasm",
      "System.Collections.Concurrent.s71l2qqufp.wasm": "System.Collections.Concurrent.wasm",
      "System.Collections.Immutable.r1wtsdf403.wasm": "System.Collections.Immutable.wasm",
      "System.Collections.NonGeneric.1j1ioxl1mw.wasm": "System.Collections.NonGeneric.wasm",
      "System.Collections.Specialized.qnhhk3bafl.wasm": "System.Collections.Specialized.wasm",
      "System.Collections.g1utvek8qj.wasm": "System.Collections.wasm",
      "System.ComponentModel.Annotations.veolr46hbh.wasm": "System.ComponentModel.Annotations.wasm",
      "System.ComponentModel.Primitives.hf8jwlptcz.wasm": "System.ComponentModel.Primitives.wasm",
      "System.ComponentModel.TypeConverter.ri3w1nfhpw.wasm": "System.ComponentModel.TypeConverter.wasm",
      "System.ComponentModel.5y3o4qq5pj.wasm": "System.ComponentModel.wasm",
      "System.Console.3mkpt7g2kd.wasm": "System.Console.wasm",
      "System.Diagnostics.DiagnosticSource.g8ajmpm5cd.wasm": "System.Diagnostics.DiagnosticSource.wasm",
      "System.IO.Pipelines.kapd30rafw.wasm": "System.IO.Pipelines.wasm",
      "System.Linq.Expressions.rxsothna1r.wasm": "System.Linq.Expressions.wasm",
      "System.Linq.3go8vyeofk.wasm": "System.Linq.wasm",
      "System.Memory.6vh06ia9tj.wasm": "System.Memory.wasm",
      "System.Net.Http.Json.59qdleq5ud.wasm": "System.Net.Http.Json.wasm",
      "System.Net.Http.2cggp8xjhq.wasm": "System.Net.Http.wasm",
      "System.Net.Primitives.yjcmep7m7h.wasm": "System.Net.Primitives.wasm",
      "System.ObjectModel.ikukleiakp.wasm": "System.ObjectModel.wasm",
      "System.Private.Uri.10mcxevr61.wasm": "System.Private.Uri.wasm",
      "System.Runtime.InteropServices.JavaScript.f7txb1es0b.wasm": "System.Runtime.InteropServices.JavaScript.wasm",
      "System.Runtime.Serialization.Primitives.b9zxhpbsq0.wasm": "System.Runtime.Serialization.Primitives.wasm",
      "System.Runtime.9r8udwp4ds.wasm": "System.Runtime.wasm",
      "System.Text.Encodings.Web.08ymq1fvcr.wasm": "System.Text.Encodings.Web.wasm",
      "System.Text.Json.lzqexd1wzq.wasm": "System.Text.Json.wasm",
      "System.Text.RegularExpressions.3ddyst6dmo.wasm": "System.Text.RegularExpressions.wasm",
      "System.m0fu6d0eya.wasm": "System.wasm",
      "System.Private.CoreLib.extootr3i2.wasm": "System.Private.CoreLib.wasm",
      "BlazorWASMDemoApp.p02rsbbdhq.wasm": "BlazorWASMDemoApp.wasm",
      "dotnet.js": "dotnet.js",
      "dotnet.native.9ih887ebfz.js": "dotnet.native.js",
      "dotnet.native.21mns4qp4i.wasm": "dotnet.native.wasm",
      "dotnet.runtime.st3wwc8rqy.js": "dotnet.runtime.js",
      "icudt_CJK.tjcz0u77k5.dat": "icudt_CJK.dat",
      "icudt_EFIGS.tptq2av103.dat": "icudt_EFIGS.dat",
      "icudt_no_CJK.lfu7j35m59.dat": "icudt_no_CJK.dat"
    },
    "jsModuleNative": {
      "dotnet.native.9ih887ebfz.js": "sha256-oS7IRiQoVt9ThQ7Y2UM3XoeY0JqPD02cg9IvRdufn2w="
    },
    "jsModuleRuntime": {
      "dotnet.runtime.st3wwc8rqy.js": "sha256-oBRKHAqZUsvCRnCzkQfB7zc45cpKLNq2NKyrG10IKx8="
    },
    "wasmNative": {
      "dotnet.native.21mns4qp4i.wasm": "sha256-RtuwNrUOdAJ5A4aS4ZmceO4ySriaYqTdC7X++6yd9lM="
    },
    "icu": {
      "icudt_CJK.tjcz0u77k5.dat": "sha256-SZLtQnRc0JkwqHab0VUVP7T3uBPSeYzxzDnpxPpUnHk=",
      "icudt_EFIGS.tptq2av103.dat": "sha256-8fItetYY8kQ0ww6oxwTLiT3oXlBwHKumbeP2pRF4yTc=",
      "icudt_no_CJK.lfu7j35m59.dat": "sha256-L7sV7NEYP37/Qr2FPCePo5cJqRgTXRwGHuwF5Q+0Nfs="
    },
    "coreAssembly": {
      "System.Runtime.InteropServices.JavaScript.f7txb1es0b.wasm": "sha256-5X6FWiZE4NSx4s9iNjfVim2lWQpcbVIsorx1vB6lyno=",
      "System.Private.CoreLib.extootr3i2.wasm": "sha256-gsloUruQ23AmGo6AbtqjOfqG8y1xpgVMxYe2bwvGN6A="
    },
    "assembly": {
      "Microsoft.AspNetCore.Components.52uh4rvy1k.wasm": "sha256-kw2lI4KKzkOFZyIITj5rLoz7acUcD78I0GgrKlBeXDE=",
      "Microsoft.AspNetCore.Components.Forms.sxuye9wrru.wasm": "sha256-ICPVStvyBHUWeKThNMH8G4t0RL/D+hjNislw0SppkG0=",
      "Microsoft.AspNetCore.Components.Web.uo04nwswhb.wasm": "sha256-fpOPH3hQavkwoze9/iFkF4PnL4UzjkhWMBcnMgTjDpg=",
      "Microsoft.AspNetCore.Components.WebAssembly.ed2mpgo6c2.wasm": "sha256-flGCF5ZOjcqmURIU2Y4ntmf/y8vp32FnKfQkB/JFpY8=",
      "Microsoft.Extensions.Configuration.pvawjtuhi4.wasm": "sha256-FaaaOUKTSpAYkiRXlXvtko5FVnHLdZR5AardvxtziDM=",
      "Microsoft.Extensions.Configuration.Abstractions.qycoarjeru.wasm": "sha256-XmI2e4usTUn8mjG/nUVaZbYCmaAS+ClB/WG24O4bc9k=",
      "Microsoft.Extensions.Configuration.Json.j66pezmcjo.wasm": "sha256-i4UmIVmRYt9sXQYxprJFXFivAl11xAcf9azr6KH7EOw=",
      "Microsoft.Extensions.DependencyInjection.vdgbrs4or0.wasm": "sha256-Ta3surCTEATmQUY4SQ/wpAIdyxK5fNnI4bm05ePwAsw=",
      "Microsoft.Extensions.DependencyInjection.Abstractions.l9716jag6r.wasm": "sha256-CW3BoWnsgf9a4j+cneSmLap7NQMZUG1BGmhxPHx7gho=",
      "Microsoft.Extensions.Logging.dypcmt2k1c.wasm": "sha256-m2ci2/3UUoSj+LBjDg24wAVdJ7/OshaoahXtPt74ak4=",
      "Microsoft.Extensions.Logging.Abstractions.41c3tqmqvg.wasm": "sha256-WNskvU9/L+/gtu95WsknYqpj9eHhUZLW6Fn6giCnx20=",
      "Microsoft.Extensions.Options.ffu15vsa0k.wasm": "sha256-S5HP9d/F/lMa/Xbn8cgaZb6xlcIE35LEPmM+9/+bJhU=",
      "Microsoft.Extensions.Primitives.wdgxpgsqcr.wasm": "sha256-zPXs1ZxaGv/gjScqkSbos0m3HyxJufpF3haxdyuT0QA=",
      "Microsoft.JSInterop.osc8jgovue.wasm": "sha256-yGWwokByYCIKRAlAW9aO0D6mYytcYnjvgXWf/gtKLls=",
      "Microsoft.JSInterop.WebAssembly.lsljofql11.wasm": "sha256-63bzxZLVvNOmTsso6iLrptxGmKBQh2HUIEGtPUrRPeQ=",
      "System.Collections.Concurrent.s71l2qqufp.wasm": "sha256-aANdOiim8BhQawVzNhhQPyAidPpW7Iz7McHn+kZt5To=",
      "System.Collections.Immutable.r1wtsdf403.wasm": "sha256-fyfE4ahd5tgdvBxv4oa9/zGmZCvyNLUDqrBefu8TwlQ=",
      "System.Collections.NonGeneric.1j1ioxl1mw.wasm": "sha256-w1usuXKNK2j74xSspdrSCx4YAYIg/2gVNfLKMRO6vuA=",
      "System.Collections.Specialized.qnhhk3bafl.wasm": "sha256-piM0MmYnXwttIvY1uZPqrjxUSn5CoS7OhgxhZd9HPr0=",
      "System.Collections.g1utvek8qj.wasm": "sha256-VPSJpKMiGBFwDn4+vKtFcOkOLcTPGavFqXo+laMf3hU=",
      "System.ComponentModel.Annotations.veolr46hbh.wasm": "sha256-15kZvKM78zdPGPO0rjQzN+whIH1OQzexxLIKVApIQGA=",
      "System.ComponentModel.Primitives.hf8jwlptcz.wasm": "sha256-bRXfjI6vH9RB0e2p87r7t9IUDxF/pT/FrGkrEmOHdIg=",
      "System.ComponentModel.TypeConverter.ri3w1nfhpw.wasm": "sha256-02bSwj8OmXpZol1nMhbMVCVexQw4p0ZiEuFQ1KrFu8g=",
      "System.ComponentModel.5y3o4qq5pj.wasm": "sha256-/TUgJRG3EZB5Bcfo9BEFJ61DIJLAJRTXeLYB1vnMd1Q=",
      "System.Console.3mkpt7g2kd.wasm": "sha256-m23pRd08wqcxINfeolmq+5fxtnvG4CKsSq3SNKPhMbU=",
      "System.Diagnostics.DiagnosticSource.g8ajmpm5cd.wasm": "sha256-cMsx1BaqBdShCb2hCIIcg1cu8DpCR6mybVTUh61tCWM=",
      "System.IO.Pipelines.kapd30rafw.wasm": "sha256-tCvlwGJAx3TJMot5V3EE7CsL75IH2QH821792tEpUhM=",
      "System.Linq.Expressions.rxsothna1r.wasm": "sha256-gUYM3MWNDl6TNcJ8oReBYd/EpG2BsTg9A6OadlCQFaY=",
      "System.Linq.3go8vyeofk.wasm": "sha256-w1TifmL7VjxlrxIRjHIVTxoGn8WCzj/JCLCmUKew3Ck=",
      "System.Memory.6vh06ia9tj.wasm": "sha256-cogZ93o17jQq3v9gfbCiEi3NkOEbeJgaWUnNTLgMIfA=",
      "System.Net.Http.Json.59qdleq5ud.wasm": "sha256-1yymUSogfaHPJpt6cEYzoQVsMr2DiSU/ZPCeD08245o=",
      "System.Net.Http.2cggp8xjhq.wasm": "sha256-sl+Kg0ptzXVfrEIy5S9bcmVHZY1wCi2wtuJV/6c58/8=",
      "System.Net.Primitives.yjcmep7m7h.wasm": "sha256-DqsumNiS0cF1FXZ5sSRsGHgAG63fChKhelkEA9f6A50=",
      "System.ObjectModel.ikukleiakp.wasm": "sha256-Plvspx59N0C/2+n8w2PHxa7F3W0cWjbzVdLpS4RHDbw=",
      "System.Private.Uri.10mcxevr61.wasm": "sha256-n5wmr/3WctmiTNAEIz0FYx7n6Z1/xUDL/OmSYe/FYB8=",
      "System.Runtime.Serialization.Primitives.b9zxhpbsq0.wasm": "sha256-v5VUTg84n8lTiYdSZXSYXy9m0WC2k99Ij2F6RCjblTc=",
      "System.Runtime.9r8udwp4ds.wasm": "sha256-Kzsatsu2mkrmgWISxpV+j3qoEdYlduvF0/1XtzHOxKM=",
      "System.Text.Encodings.Web.08ymq1fvcr.wasm": "sha256-QPumUm/+bRPi/T+QpPMfrlCeezAnzRk6CmD/iBskgiw=",
      "System.Text.Json.lzqexd1wzq.wasm": "sha256-IaXEa4N/yg5dilz3i0BgYNyT32WxV70Ymxyyt7NI1dE=",
      "System.Text.RegularExpressions.3ddyst6dmo.wasm": "sha256-J0h0LpWzXEYF0E+lUOiWbLF6UobUv3nu0XKBs3nMIoQ=",
      "System.m0fu6d0eya.wasm": "sha256-hkGLo/MuT/FJ0Xf4XUL0D2VA4dZV532GHNB1JicxLko=",
      "BlazorWASMDemoApp.p02rsbbdhq.wasm": "sha256-+dod6t7MHDFh91p2vOKsbMWCc74M3TVHaRwyXkmHX6k="
    }
  },
  "cacheBootResources": true,
  "debugLevel": 0,
  "linkerEnabled": true,
  "globalizationMode": "sharded",
  "extensions": {
    "blazor": {}
  }
}